{"historialServiciosMantenimiento":"null","estado":"Activo","estilo":"Compacto","color":"azul","mpg":"32","sedePertenencia":"Alajuela","numVim":"A1B2C3D4","marca":"Hyundai","listaCoordenadas":"null","capacidadMaletas":"3","kilometraje":"33000.0","transmision":"Automatica","rentado":"true","anho":"2006","costoPorDia":"2300.0","numPuertas":"4","placa":"BBB111","capacidad":"5"}{"historialServiciosMantenimiento":"null","estado":"Activo","estilo":"Compacto","color":"azul","mpg":"32","sedePertenencia":"Alajuela","numVim":"A1B2C3D4","marca":"Hyundai","listaCoordenadas":"null","capacidadMaletas":"3","kilometraje":"33000.0","transmision":"Automatica","rentado":"true","anho":"2006","costoPorDia":"2300.0","numPuertas":"4","placa":"BBB111","capacidad":"5"}{"historialServiciosMantenimiento":"null","estado":"Activo","estilo":"Compacto","color":"azul","mpg":"32","sedePertenencia":"Alajuela","numVim":"A1B2C3D4","marca":"Hyundai","listaCoordenadas":"null","capacidadMaletas":"3","kilometraje":"33000.0","transmision":"Automatica","rentado":"true","anho":"2006","costoPorDia":"2300.0","numPuertas":"4","placa":"BBB111","capacidad":"5"}{"historialServiciosMantenimiento":"null","estado":"Activo","estilo":"Compacto","color":"azul","mpg":"32","sedePertenencia":"Alajuela","numVim":"A1B2C3D4","marca":"Hyundai","listaCoordenadas":"null","capacidadMaletas":"3","kilometraje":"33000.0","transmision":"Automatica","rentado":"true","anho":"2006","costoPorDia":"2300.0","numPuertas":"4","placa":"BBB111","capacidad":"5"}